quke/__init__.py
quke/conf/__init__.py
quke/conf/config.yaml
quke/conf/embedding/cohere.yaml
quke/conf/embedding/hf_r.yaml
quke/conf/embedding/huggingface.yaml
quke/conf/embedding/openai.yaml
quke/conf/experiment/llama2.yaml
quke/conf/experiment/openai.yaml
quke/conf/experiment/openaihf.yaml
quke/conf/llm/cohere.yaml
quke/conf/llm/falcon7b.yaml
quke/conf/llm/gemini.yaml
quke/conf/llm/gpt4o.yaml
quke/conf/llm/litellm.yaml
quke/conf/llm/llama2.yaml
quke/conf/llm/mistral.yaml
quke/conf/question/eps.yaml
quke/conf/question/growth.yaml
quke/conf/question/tabulation.yaml
quke/embed.py
quke/llm_chat.py
quke/quke.py
quke/rate_limiter.py
quke/templates/chat_session.html.jinja
quke/templates/chat_session.logging.jinja
quke/templates/chat_session.md.jinja
quke/trial questions.txt
quke-0.6.0.dist-info/METADATA
quke-0.6.0.dist-info/WHEEL
quke-0.6.0.dist-info/entry_points.txt
quke-0.6.0.dist-info/RECORD
