Metadata-Version: 2.1
Name: quke
Version: 0.6.0
Summary: Compare the answering capabilities of different LLMs - for example LlaMa, GPT4o, Mistral, Claude, Cohere, others - against user provided document(s) and questions.
Home-page: https://github.com/EJOOSTEROP/quke
License: MIT
Keywords: ML,LLM,compare,chat,semantic search
Author: Erik Oosterop
Maintainer: Erik Oosterop
Requires-Python: >=3.11,<4.0
Classifier: License :: OSI Approved :: MIT License
Classifier: Programming Language :: Python :: 3
Classifier: Programming Language :: Python :: 3.11
Classifier: Programming Language :: Python :: 3.12
Requires-Dist: hydra-core (>=1.3.2,<2.0.0)
Requires-Dist: jinja2 (>=3.1.4,<4.0.0)
Requires-Dist: langchain-chroma (>=0.1.2,<0.2.0)
Requires-Dist: langchain-cohere (>=0.1.9,<0.2.0)
Requires-Dist: langchain-community (>=0.2.10,<0.3.0)
Requires-Dist: langchain-core (>=0.2.25,<0.3.0)
Requires-Dist: langchain-google-genai (>=1.0.8,<2.0.0)
Requires-Dist: langchain-huggingface (>=0.0.3,<0.0.4)
Requires-Dist: langchain-mistralai (>=0.1.11,<0.2.0)
Requires-Dist: langchain-openai (>=0.1.19,<0.2.0)
Requires-Dist: lark (>=1.1.7,<2.0.0)
Requires-Dist: litellm (>=1.42.5,<2.0.0)
Requires-Dist: pymupdf (>=1.24.9,<2.0.0)
Requires-Dist: python-dotenv (>=1.0.1,<2.0.0)
Requires-Dist: replicate (>=0.30.1,<0.31.0)
Requires-Dist: rich (>=13.5.2,<14.0.0)
Requires-Dist: sentence-transformers (>=3.0.1,<4.0.0)
Project-URL: Documentation, https://github.com/EJOOSTEROP/quke
Project-URL: Repository, https://github.com/EJOOSTEROP/quke
